{
  "products": [
    {
      "id": "1",
      "name": "Laptop",
      "price": 100000
    },
    {
      "id": "2",
      "name": "HeadPhone",
      "price": 1000
    },
    {
      "id": "3",
      "name": "TV",
      "price": 30000
    },
    {
      "id": "4",
      "name": "Mobile",
      "price": "15000"
    },
    {
      "id": "e808"
    },
    {
      "id": "1a13"
    },
    {
      "id": "6",
      "name": "Pen",
      "price": "100"
    },
    {
      "id": "6",
      "name": "Pen",
      "price": "100"
    },
    {
      "id": "6",
      "name": "Pen",
      "price": "100"
    },
    {
      "id": "415c"
    },
    {
      "id": "6801"
    },
    {
      "id": "4cb6"
    },
    {
      "id": "e409"
    },
    {
      "id": "c2a9"
    },
    {
      "id": "d48e"
    },
    {
      "id": "3096"
    },
    {
      "id": "7d6f"
    },
    {
      "id": "019b"
    },
    {
      "id": "0010"
    },
    {
      "id": "9e42"
    },
    {
      "id": "c3d6"
    },
    {
      "id": "ee5a"
    },
    {
      "id": "e72a"
    },
    {
      "id": "abd9"
    },
    {
      "id": "93c3"
    },
    {
      "id": "2990"
    },
    {
      "id": "b598"
    },
    {
      "id": "950d"
    },
    {
      "id": "ceb3"
    },
    {
      "id": "7793"
    },
    {
      "id": "88ed"
    },
    {
      "id": "674d"
    },
    {
      "id": "3b32"
    },
    {
      "id": "6a79"
    },
    {
      "id": "8e7e"
    },
    {
      "id": "93c3"
    },
    {
      "id": "1958"
    },
    {
      "id": "21f7"
    },
    {
      "id": "0e89"
    },
    {
      "id": "3889"
    },
    {
      "id": "b2c3"
    },
    {
      "id": "3f1f"
    },
    {
      "id": "4844"
    },
    {
      "id": "5422"
    },
    {
      "id": "b07d"
    },
    {
      "id": "95a5"
    },
    {
      "id": "f75d"
    },
    {
      "id": "cb24"
    },
    {
      "id": "006c"
    },
    {
      "id": "d131"
    },
    {
      "id": "eae3"
    },
    {
      "id": "a437"
    },
    {
      "id": "2698"
    },
    {
      "id": "d56e"
    },
    {
      "id": "5853"
    },
    {
      "id": "c099"
    },
    {
      "id": "a477"
    },
    {
      "id": "d151"
    },
    {
      "id": "f1c8"
    },
    {
      "id": "ac59"
    },
    {
      "id": "1f7b"
    },
    {
      "id": "37aa"
    },
    {
      "id": "8a07"
    },
    {
      "id": "1780"
    },
    {
      "id": "2c03"
    },
    {
      "id": "6a20"
    },
    {
      "id": "7768"
    },
    {
      "id": "3f72"
    },
    {
      "id": "d488"
    },
    {
      "id": "4bf0"
    },
    {
      "id": "f76e"
    },
    {
      "id": "666f"
    },
    {
      "id": "3050"
    },
    {
      "id": "8d82"
    },
    {
      "id": "c4d2"
    },
    {
      "id": "81be"
    },
    {
      "id": "ec68"
    },
    {
      "id": "3e6f"
    },
    {
      "id": "5848"
    },
    {
      "id": "5cb8"
    },
    {
      "id": "1e17"
    },
    {
      "id": "3534"
    },
    {
      "id": "2b58"
    },
    {
      "id": "2781"
    },
    {
      "id": "8952"
    },
    {
      "id": "acf8"
    },
    {
      "id": "868a"
    },
    {
      "id": "89dc"
    },
    {
      "id": "2d21"
    }
  ]
}